pep_517_example/builder.py
pep_517_example/__main__.py
pep_517_example-1.dist-info/METADATA
pep_517_example-1.dist-info/WHEEL
