Metadata-Version: 2.1
Name: pep_517_example
Version: 1
Summary: Example of PEP-517 builder that uses wheelfile
Keywords: wheel,packaging,pip,build,pep-517
Classifier: Intended Audience :: Developers
Classifier: License :: OSI Approved :: MIT License
Author: Błażej Michalik
Home-page: https://github.com/MrMino/wheelfile
Requires-Dist: wheelfile
